pokpok_sdk/__init__.py
pokpok_sdk/config.py
pokpok_sdk/constants.py
pokpok_sdk/exceptions.py
pokpok_sdk/models.py
pokpok_sdk/payg_api.py
pokpok_sdk/protocol_abi.json
pokpok_sdk/spread_api.py
pokpok_sdk/utils.py
pokpok_sdk/web2.py
pokpok_sdk/web3.py
pokpok_sdk-0.1.6.dist-info/METADATA
pokpok_sdk-0.1.6.dist-info/WHEEL
pokpok_sdk-0.1.6.dist-info/top_level.txt
pokpok_sdk-0.1.6.dist-info/RECORD
